dcbench/__init__.py
dcbench/__main__.py
dcbench/config.py
dcbench/constants.py
dcbench/version.py
dcbench/common/__init__.py
dcbench/common/artefact.py
dcbench/common/artifact.py
dcbench/common/baseline.py
dcbench/common/bundle.py
dcbench/common/download_utils.py
dcbench/common/method.py
dcbench/common/modeling.py
dcbench/common/problem.py
dcbench/common/result.py
dcbench/common/solution.py
dcbench/common/solve.py
dcbench/common/table.py
dcbench/common/task.py
dcbench/common/utils.py
dcbench/tasks/__init__.py
dcbench/tasks/budgetclean/__init__.py
dcbench/tasks/budgetclean/baselines.py
dcbench/tasks/budgetclean/common.py
dcbench/tasks/budgetclean/problem.py
dcbench/tasks/miniclean/__init__.py
dcbench/tasks/miniclean/bank.py
dcbench/tasks/miniclean/common.py
dcbench/tasks/miniclean/problem.py
dcbench/tasks/minidata/__init__.py
dcbench/tasks/minidata/unagi_configs.py
dcbench/tasks/slice/__init__.py
dcbench/tasks/slice/build_problems.py
dcbench/tasks/slice_discovery/__init__.py
dcbench/tasks/slice_discovery/baselines.py
dcbench/tasks/slice_discovery/build_problems.py
dcbench/tasks/slice_discovery/domino.py
dcbench/tasks/slice_discovery/metrics.py
dcbench/tasks/slice_discovery/problem.py
dcbench-0.0.4.dist-info/LICENSE.md
dcbench-0.0.4.dist-info/METADATA
dcbench-0.0.4.dist-info/WHEEL
dcbench-0.0.4.dist-info/top_level.txt
dcbench-0.0.4.dist-info/RECORD
