Metadata-Version: 2.1
Name: dcbench
Version: 0.0.4
Summary: This is a benchmark that tests various data-centric aspects of improving the quality of machine learning workflows.
Home-page: UNKNOWN
Author: https://github.com/data-centric-ai/dcbench
Author-email: sabri@eyuboglu.us
License: Apache 2.0
Platform: UNKNOWN
Classifier: Programming Language :: Python
Classifier: Programming Language :: Python :: 3
Classifier: Programming Language :: Python :: 3.7
Classifier: Programming Language :: Python :: 3.8
Classifier: Programming Language :: Python :: 3.9
Classifier: Topic :: Scientific/Engineering :: Artificial Intelligence
Requires-Python: >=3.7.0
License-File: LICENSE.md
Requires-Dist: click (>=8.0.0)
Requires-Dist: pyyaml (>=5.4)
Requires-Dist: pre-commit
Requires-Dist: pandas
Requires-Dist: numpy (>=1.18.0)
Requires-Dist: ujson
Requires-Dist: jsonlines (>=1.2.0)
Requires-Dist: tqdm (>=4.49.0)
Requires-Dist: scikit-learn
Requires-Dist: meerkat-ml[dev,ml,vision]
Provides-Extra: dev
Requires-Dist: black (==21.5b0) ; extra == 'dev'
Requires-Dist: isort (>=5.7.0) ; extra == 'dev'
Requires-Dist: flake8 (>=3.8.4) ; extra == 'dev'
Requires-Dist: mypy (>=0.9) ; extra == 'dev'
Requires-Dist: docformatter (>=1.4) ; extra == 'dev'
Requires-Dist: pytest-cov (>=2.10.1) ; extra == 'dev'
Requires-Dist: sphinx-rtd-theme (>=0.5.1) ; extra == 'dev'
Requires-Dist: nbsphinx (>=0.8.0) ; extra == 'dev'
Requires-Dist: recommonmark (>=0.7.1) ; extra == 'dev'
Requires-Dist: parameterized ; extra == 'dev'
Requires-Dist: pre-commit (>=2.9.3) ; extra == 'dev'
Requires-Dist: sphinx-autobuild ; extra == 'dev'
Requires-Dist: google-cloud-storage ; extra == 'dev'
Requires-Dist: furo ; extra == 'dev'
